tmcp_runner/__init__.py
tmcp_runner/runner.py
tmcp_runner/utils.py
tmcp_runner-0.4.0.dist-info/licenses/LICENSE
tmcp_runner-0.4.0.dist-info/METADATA
tmcp_runner-0.4.0.dist-info/WHEEL
tmcp_runner-0.4.0.dist-info/top_level.txt
tmcp_runner-0.4.0.dist-info/RECORD
