Metadata-Version: 2.4
Name: tmcp_runner
Version: 0.4.0
Summary: Python library for embedding MCP (Model Context Protocol) capabilities into applications, like Claude Desktop and Cursor do internally. Sponsored by TowardsAGI.
Author-email: TowardsMCP Developers <support@towardsagi.ai>
Maintainer-email: Mansoor Pasha I <support@towardsagi.ai>
Project-URL: Homepage, https://towardsmcp.com
Project-URL: Repository, https://github.com/QuantumicsAI/tmcp_runner
Project-URL: Sponsor, https://towardsagi.ai
Project-URL: Documentation, https://github.com/QuantumicsAI/tmcp_runner#readme
Keywords: mcp,model-context-protocol,anthropic,ai,llm,tools,agents
Classifier: Development Status :: 4 - Beta
Classifier: Intended Audience :: Developers
Classifier: License :: OSI Approved :: MIT License
Classifier: Programming Language :: Python :: 3
Classifier: Programming Language :: Python :: 3.10
Classifier: Programming Language :: Python :: 3.11
Classifier: Programming Language :: Python :: 3.12
Classifier: Topic :: Software Development :: Libraries :: Python Modules
Classifier: Topic :: Scientific/Engineering :: Artificial Intelligence
Requires-Python: >=3.10
License-File: LICENSE
Requires-Dist: mcp>=1.0.0
Requires-Dist: httpx>=0.27.0
Requires-Dist: httpx-sse>=0.4.0
Requires-Dist: pydantic>=2.0.0
Provides-Extra: dev
Requires-Dist: pytest>=7.0.0; extra == "dev"
Requires-Dist: pytest-asyncio>=0.21.0; extra == "dev"
Requires-Dist: black>=23.0.0; extra == "dev"
Requires-Dist: ruff>=0.1.0; extra == "dev"
Dynamic: license-file
